Workbook
Name ADR_Base: Assumptions!$B$3
Name CPR: Assumptions!$B$6
Name FeePct: Assumptions!$B$7
Name InitPool: Assumptions!$B$2
Name MezzPct: Assumptions!$B$9
Name MezzRate: Assumptions!$B$13
Name Mz_Notes: TotalNotes*MezzPct
Name OCpct: Assumptions!$B$11
Name Port_Defaults: Portfolio_CF!$E$2:$E$37
Name ProjMonths: Assumptions!$B$15
Name RecLag: Assumptions!$B$16
Name RecoveryRate: Assumptions!$B$5
Name SeniorPct: Assumptions!$B$8
Name SeniorRate: Assumptions!$B$12
Name Sr_Notes: TotalNotes*SeniorPct
Name TotalNotes: InitPool*(1-OCpct)

Sheet README
A1: ABS Cash Flow Showcase – Sadaf Davre
A3: How to use:
A4: 1) Change assumptions as needed on the 'Assumptions' sheet (defaults, recoveries, prepayments, fees, tranche sizes/rates).
A5: 2) The 'Portfolio_CF' sheet rolls monthly balances & collections using formulas.
A6: 3) The 'Waterfall' sheet allocates collections to Senior → Mezz → Equity with priority of payments.
A7: 4) 'Tranche_Summary' computes IRR and WAL; compare Base vs. Stress by adjusting assumptions.
A9: Includes 'Dashboard' sheet for a clean one‑pager with key metrics and a chart.

Sheet Assumptions
A1: Item | B1: Value | C1: Notes
A2: Initial Pool Balance | B2: 5046400 | C2: Sum of principals across 150 synthetic loans
A3: Annual Default Rate (Base) | B3: 0.05 | C3: Constant hazard on beginning balance
A4: Annual Default Rate (Stress) | B4: 0.12 | C4: Higher stress
A5: Recovery Rate | B5: 0.6 | C5: Applied to defaults with 3-month lag
A6: Annual Prepayment Rate | B6: 0.03 | C6: CPR approximation
A7: Servicing/Fee as % of Collections | B7: 0.01 | C7: Simple fee on monthly collections
A8: Senior Tranche % of Notes | B8: 0.7 | C8: Share of total notes
A9: Mezz Tranche % of Notes | B9: 0.2 | C9: Share of total notes
A10: Equity Tranche % of Notes | B10: 0.1 | C10: Share of total notes
A11: Overcollateralization % | B11: 0.05 | C11: Pool balance exceeds notes by this % at closing
A12: Senior Rate (annual) | B12: 0.06 | C12: Coupon on Senior
A13: Mezz Rate (annual) | B13: 0.09 | C13: Coupon on Mezz
... A16: Recovery Lag (months) | B16: 3 | C16: Timing for recoveries

Sheet Loans
A1: LoanID | B1: Segment | C1: Principal | D1: Rate_Annual | E1: Term_Months | F1: StartDate | G1: DefaultProb_Annual | H1: RecoveryRate
A2: L001 | B2: SmallBiz | C2: 28700 | D2: 0.169 | E2: 30 | F2: 2026-01-01 | G2: 0.0664 | H2: 0.49
A3: L002 | B3: SmallBiz | C3: 57500 | D3: 0.0887 | E3: 32 | F3: 2026-01-01 | G3: 0.0473 | H3: 0.58
A4: L003 | B4: SmallBiz | C4: 46600 | D4: 0.0774 | E4: 20 | F4: 2026-01-01 | G4: 0.063 | H4: 0.6
A5: L004 | B5: WholeBusiness | C5: 39900 | D5: 0.1187 | E5: 25 | F5: 2026-01-01 | G5: 0.0568 | H5: 0.54
A6: L005 | B6: SmallBiz | C6: 17800 | D6: 0.1783 | E6: 33 | F6: 2026-01-01 | G6: 0.0668 | H6: 0.61
A7: L006 | B7: EquipmentLease | C7: 17800 | D7: 0.089 | E7: 30 | F7: 2026-01-01 | G7: 0.052 | H7: 0.67
A8: L007 | B8: SmallBiz | C8: 12900 | D8: 0.1407 | E8: 35 | F8: 2026-01-01 | G8: 0.0758 | H8: 0.59
A9: L008 | B9: EquipmentLease | C9: 53300 | D9: 0.1514 | E9: 27 | F9: 2026-01-01 | G9: 0.0344 | H9: 0.56
A10: L009 | B10: WholeBusiness | C10: 40100 | D10: 0.0885 | E10: 36 | F10: 2026-01-01 | G10: 0.0757 | H10: 0.53
A11: L010 | B11: WholeBusiness | C11: 45400 | D11: 0.1474 | E11: 34 | F11: 2026-01-01 | G11: 0.0529 | H11: 0.57
A12: L011 | B12: SmallBiz | C12: 11000 | D12: 0.1041 | E12: 36 | F12: 2026-01-01 | G12: 0.0899 | H12: 0.51
A13: L012 | B13: WholeBusiness | C13: 58500 | D13: 0.1359 | E13: 22 | F13: 2026-01-01 | G13: 0.0612 | H13: 0.52
... A151: L150 | B151: SmallBiz | C151: 23900 | D151: 0.0702 | E151: 24 | F151: 2026-01-01 | G151: 0.0926 | H151: 0.5

Sheet Portfolio_CF
A1: Month | B1: Beg_Bal | C1: Sched_Interest | D1: Sched_Principal | E1: Defaults | F1: Recoveries | G1: Prepayments | H1: Fees | I1: Collections | J1: End_Bal
A2: 1 | B2: =InitPool -> 5046400 | C2: =B2*0.122102/12 -> 51347.961 | D2: =MIN(B2,B2/36) -> 140177.78 | E2: =B2*(ADR_Base/12) -> 21026.667 | F2: =IF(1<=RecLag,0,INDEX(Port_Defaults,1-RecLag)*RecoveryRate) -> 0 | G2: =B2*(CPR/12) -> 12616 | H2: =FeePct*(C2+D2+F2) -> 1915.2574 | I2: =C2+D2+F2-E2-G2-H2 -> 155967.81 | J2: =B2-(D2+E2+G2) -> 4872579.6
A3: 2 | B3: =J2 -> 4872579.6 | C3: =B3*0.122102/12 -> 49579.309 | D3: =MIN(B3,B3/35) -> 139216.56 | E3: =B3*(ADR_Base/12) -> 20302.415 | F3: =IF(2<=RecLag,0,INDEX(Port_Defaults,2-RecLag)*RecoveryRate) -> 0 | G3: =B3*(CPR/12) -> 12181.449 | H3: =FeePct*(C3+D3+F3) -> 1887.9587 | I3: =C3+D3+F3-E3-G3-H3 -> 154424.05 | J3: =B3-(D3+E3+G3) -> 4700879.1
A4: 3 | B4: =J3 -> 4700879.1 | C4: =B4*0.122102/12 -> 47832.229 | D4: =MIN(B4,B4/34) -> 138261.15 | E4: =B4*(ADR_Base/12) -> 19586.996 | F4: =IF(3<=RecLag,0,INDEX(Port_Defaults,3-RecLag)*RecoveryRate) -> 0 | G4: =B4*(CPR/12) -> 11752.198 | H4: =FeePct*(C4+D4+F4) -> 1860.9338 | I4: =C4+D4+F4-E4-G4-H4 -> 152893.25 | J4: =B4-(D4+E4+G4) -> 4531278.8
A5: 4 | B5: =J4 -> 4531278.8 | C5: =B5*0.122102/12 -> 46106.517 | D5: =MIN(B5,B5/33) -> 137311.48 | E5: =B5*(ADR_Base/12) -> 18880.328 | F5: =IF(4<=RecLag,0,INDEX(Port_Defaults,4-RecLag)*RecoveryRate) -> 12616 | G5: =B5*(CPR/12) -> 11328.197 | H5: =FeePct*(C5+D5+F5) -> 1960.34 | I5: =C5+D5+F5-E5-G5-H5 -> 163865.13 | J5: =B5-(D5+E5+G5) -> 4363758.8
A6: 5 | B6: =J5 -> 4363758.8 | C6: =B6*0.122102/12 -> 44401.973 | D6: =MIN(B6,B6/32) -> 136367.46 | E6: =B6*(ADR_Base/12) -> 18182.328 | F6: =IF(5<=RecLag,0,INDEX(Port_Defaults,5-RecLag)*RecoveryRate) -> 12181.449 | G6: =B6*(CPR/12) -> 10909.397 | H6: =FeePct*(C6+D6+F6) -> 1929.5088 | I6: =C6+D6+F6-E6-G6-H6 -> 161929.65 | J6: =B6-(D6+E6+G6) -> 4198299.6
A7: 6 | B7: =J6 -> 4198299.6 | C7: =B7*0.122102/12 -> 42718.398 | D7: =MIN(B7,B7/31) -> 135429.02 | E7: =B7*(ADR_Base/12) -> 17492.915 | F7: =IF(6<=RecLag,0,INDEX(Port_Defaults,6-RecLag)*RecoveryRate) -> 11752.198 | G7: =B7*(CPR/12) -> 10495.749 | H7: =FeePct*(C7+D7+F7) -> 1898.9962 | I7: =C7+D7+F7-E7-G7-H7 -> 160011.96 | J7: =B7-(D7+E7+G7) -> 4034881.9
A8: 7 | B8: =J7 -> 4034881.9 | C8: =B8*0.122102/12 -> 41055.596 | D8: =MIN(B8,B8/30) -> 134496.06 | E8: =B8*(ADR_Base/12) -> 16812.008 | F8: =IF(7<=RecLag,0,INDEX(Port_Defaults,7-RecLag)*RecoveryRate) -> 11328.197 | G8: =B8*(CPR/12) -> 10087.205 | H8: =FeePct*(C8+D8+F8) -> 1868.7986 | I8: =C8+D8+F8-E8-G8-H8 -> 158111.85 | J8: =B8-(D8+E8+G8) -> 3873486.6
A9: 8 | B9: =J8 -> 3873486.6 | C9: =B9*0.122102/12 -> 39413.372 | D9: =MIN(B9,B9/29) -> 133568.5 | E9: =B9*(ADR_Base/12) -> 16139.528 | F9: =IF(8<=RecLag,0,INDEX(Port_Defaults,8-RecLag)*RecoveryRate) -> 10909.397 | G9: =B9*(CPR/12) -> 9683.7166 | H9: =FeePct*(C9+D9+F9) -> 1838.9127 | I9: =C9+D9+F9-E9-G9-H9 -> 156229.12 | J9: =B9-(D9+E9+G9) -> 3714094.9
A10: 9 | B10: =J9 -> 3714094.9 | C10: =B10*0.122102/12 -> 37791.535 | D10: =MIN(B10,B10/28) -> 132646.25 | E10: =B10*(ADR_Base/12) -> 15475.395 | F10: =IF(9<=RecLag,0,INDEX(Port_Defaults,9-RecLag)*RecoveryRate) -> 10495.749 | G10: =B10*(CPR/12) -> 9285.2372 | H10: =FeePct*(C10+D10+F10) -> 1809.3353 | I10: =C10+D10+F10-E10-G10-H10 -> 154363.56 | J10: =B10-(D10+E10+G10) -> 3556688
A11: 10 | B11: =J10 -> 3556688 | C11: =B11*0.122102/12 -> 36189.893 | D11: =MIN(B11,B11/27) -> 131729.19 | E11: =B11*(ADR_Base/12) -> 14819.533 | F11: =IF(10<=RecLag,0,INDEX(Port_Defaults,10-RecLag)*RecoveryRate) -> 10087.205 | G11: =B11*(CPR/12) -> 8891.72 | H11: =FeePct*(C11+D11+F11) -> 1780.0628 | I11: =C11+D11+F11-E11-G11-H11 -> 152514.97 | J11: =B11-(D11+E11+G11) -> 3401247.6
A12: 11 | B12: =J11 -> 3401247.6 | C12: =B12*0.122102/12 -> 34608.261 | D12: =MIN(B12,B12/26) -> 130817.21 | E12: =B12*(ADR_Base/12) -> 14171.865 | F12: =IF(11<=RecLag,0,INDEX(Port_Defaults,11-RecLag)*RecoveryRate) -> 9683.7166 | G12: =B12*(CPR/12) -> 8503.1189 | H12: =FeePct*(C12+D12+F12) -> 1751.0919 | I12: =C12+D12+F12-E12-G12-H12 -> 150683.12 | J12: =B12-(D12+E12+G12) -> 3247755.4
A13: 12 | B13: =J12 -> 3247755.4 | C13: =B13*0.122102/12 -> 33046.452 | D13: =MIN(B13,B13/25) -> 129910.21 | E13: =B13*(ADR_Base/12) -> 13532.314 | F13: =IF(12<=RecLag,0,INDEX(Port_Defaults,12-RecLag)*RecoveryRate) -> 9285.2372 | G13: =B13*(CPR/12) -> 8119.3884 | H13: =FeePct*(C13+D13+F13) -> 1722.419 | I13: =C13+D13+F13-E13-G13-H13 -> 148867.78 | J13: =B13-(D13+E13+G13) -> 3096193.5
A14: 13 | B14: =J13 -> 3096193.5 | C14: =B14*0.122102/12 -> 31504.284 | D14: =MIN(B14,B14/24) -> 129008.06 | E14: =B14*(ADR_Base/12) -> 12900.806 | F14: =IF(13<=RecLag,0,INDEX(Port_Defaults,13-RecLag)*RecoveryRate) -> 8891.72 | G14: =B14*(CPR/12) -> 7740.4836 | H14: =FeePct*(C14+D14+F14) -> 1694.0407 | I14: =C14+D14+F14-E14-G14-H14 -> 147068.73 | J14: =B14-(D14+E14+G14) -> 2946544.1
A15: 14 | B15: =J14 -> 2946544.1 | C15: =B15*0.122102/12 -> 29981.577 | D15: =MIN(B15,B15/23) -> 128110.61 | E15: =B15*(ADR_Base/12) -> 12277.267 | F15: =IF(14<=RecLag,0,INDEX(Port_Defaults,14-RecLag)*RecoveryRate) -> 8503.1189 | G15: =B15*(CPR/12) -> 7366.3603 | H15: =FeePct*(C15+D15+F15) -> 1665.9531 | I15: =C15+D15+F15-E15-G15-H15 -> 145285.73 | J15: =B15-(D15+E15+G15) -> 2798789.9
A16: 15 | B16: =J15 -> 2798789.9 | C16: =B16*0.122102/12 -> 28478.153 | D16: =MIN(B16,B16/22) -> 127217.72 | E16: =B16*(ADR_Base/12) -> 11661.624 | F16: =IF(15<=RecLag,0,INDEX(Port_Defaults,15-RecLag)*RecoveryRate) -> 8119.3884 | G16: =B16*(CPR/12) -> 6996.9747 | H16: =FeePct*(C16+D16+F16) -> 1638.1526 | I16: =C16+D16+F16-E16-G16-H16 -> 143518.51 | J16: =B16-(D16+E16+G16) -> 2652913.5
A17: 16 | B17: =J16 -> 2652913.5 | C17: =B17*0.122102/12 -> 26993.837 | D17: =MIN(B17,B17/21) -> 126329.22 | E17: =B17*(ADR_Base/12) -> 11053.806 | F17: =IF(16<=RecLag,0,INDEX(Port_Defaults,16-RecLag)*RecoveryRate) -> 7740.4836 | G17: =B17*(CPR/12) -> 6632.2839 | H17: =FeePct*(C17+D17+F17) -> 1610.6354 | I17: =C17+D17+F17-E17-G17-H17 -> 141766.81 | J17: =B17-(D17+E17+G17) -> 2508898.2
A18: 17 | B18: =J17 -> 2508898.2 | C18: =B18*0.122102/12 -> 25528.458 | D18: =MIN(B18,B18/20) -> 125444.91 | E18: =B18*(ADR_Base/12) -> 10453.743 | F18: =IF(17<=RecLag,0,INDEX(Port_Defaults,17-RecLag)*RecoveryRate) -> 7366.3603 | G18: =B18*(CPR/12) -> 6272.2456 | H18: =FeePct*(C18+D18+F18) -> 1583.3973 | I18: =C18+D18+F18-E18-G18-H18 -> 140030.34 | J18: =B18-(D18+E18+G18) -> 2366727.3
A19: 18 | B19: =J18 -> 2366727.3 | C19: =B19*0.122102/12 -> 24081.845 | D19: =MIN(B19,B19/19) -> 124564.6 | E19: =B19*(ADR_Base/12) -> 9861.3639 | F19: =IF(18<=RecLag,0,INDEX(Port_Defaults,18-RecLag)*RecoveryRate) -> 6996.9747 | G19: =B19*(CPR/12) -> 5916.8183 | H19: =FeePct*(C19+D19+F19) -> 1556.4342 | I19: =C19+D19+F19-E19-G19-H19 -> 138308.8 | J19: =B19-(D19+E19+G19) -> 2226384.6
A20: 19 | B20: =J19 -> 2226384.6 | C20: =B20*0.122102/12 -> 22653.834 | D20: =MIN(B20,B20/18) -> 123688.03 | E20: =B20*(ADR_Base/12) -> 9276.6023 | F20: =IF(19<=RecLag,0,INDEX(Port_Defaults,19-RecLag)*RecoveryRate) -> 6632.2839 | G20: =B20*(CPR/12) -> 5565.9614 | H20: =FeePct*(C20+D20+F20) -> 1529.7415 | I20: =C20+D20+F20-E20-G20-H20 -> 136601.84 | J20: =B20-(D20+E20+G20) -> 2087854
A21: 20 | B21: =J20 -> 2087854 | C21: =B21*0.122102/12 -> 21244.262 | D21: =MIN(B21,B21/17) -> 122814.94 | E21: =B21*(ADR_Base/12) -> 8699.3915 | F21: =IF(20<=RecLag,0,INDEX(Port_Defaults,20-RecLag)*RecoveryRate) -> 6272.2456 | G21: =B21*(CPR/12) -> 5219.6349 | H21: =FeePct*(C21+D21+F21) -> 1503.3145 | I21: =C21+D21+F21-E21-G21-H21 -> 134909.11 | J21: =B21-(D21+E21+G21) -> 1951120
A22: 21 | B22: =J21 -> 1951120 | C22: =B22*0.122102/12 -> 19852.971 | D22: =MIN(B22,B22/16) -> 121945 | E22: =B22*(ADR_Base/12) -> 8129.6667 | F22: =IF(21<=RecLag,0,INDEX(Port_Defaults,21-RecLag)*RecoveryRate) -> 5916.8183 | G22: =B22*(CPR/12) -> 4877.8 | H22: =FeePct*(C22+D22+F22) -> 1477.1479 | I22: =C22+D22+F22-E22-G22-H22 -> 133230.17 | J22: =B22-(D22+E22+G22) -> 1816167.5
A23: 22 | B23: =J22 -> 1816167.5 | C23: =B23*0.122102/12 -> 18479.807 | D23: =MIN(B23,B23/15) -> 121077.84 | E23: =B23*(ADR_Base/12) -> 7567.3647 | F23: =IF(22<=RecLag,0,INDEX(Port_Defaults,22-RecLag)*RecoveryRate) -> 5565.9614 | G23: =B23*(CPR/12) -> 4540.4188 | H23: =FeePct*(C23+D23+F23) -> 1451.236 | I23: =C23+D23+F23-E23-G23-H23 -> 131564.58 | J23: =B23-(D23+E23+G23) -> 1682981.9
A24: 23 | B24: =J23 -> 1682981.9 | C24: =B24*0.122102/12 -> 17124.621 | D24: =MIN(B24,B24/14) -> 120212.99 | E24: =B24*(ADR_Base/12) -> 7012.4246 | F24: =IF(23<=RecLag,0,INDEX(Port_Defaults,23-RecLag)*RecoveryRate) -> 5219.6349 | G24: =B24*(CPR/12) -> 4207.4548 | H24: =FeePct*(C24+D24+F24) -> 1425.5725 | I24: =C24+D24+F24-E24-G24-H24 -> 129911.8 | J24: =B24-(D24+E24+G24) -> 1551549
A25: 24 | B25: =J24 -> 1551549 | C25: =B25*0.122102/12 -> 15787.27 | D25: =MIN(B25,B25/13) -> 119349.93 | E25: =B25*(ADR_Base/12) -> 6464.7877 | F25: =IF(24<=RecLag,0,INDEX(Port_Defaults,24-RecLag)*RecoveryRate) -> 4877.8 | G25: =B25*(CPR/12) -> 3878.8726 | H25: =FeePct*(C25+D25+F25) -> 1400.15 | I25: =C25+D25+F25-E25-G25-H25 -> 128271.19 | J25: =B25-(D25+E25+G25) -> 1421855.5
A26: 25 | B26: =J25 -> 1421855.5 | C26: =B26*0.122102/12 -> 14467.616 | D26: =MIN(B26,B26/12) -> 118487.95 | E26: =B26*(ADR_Base/12) -> 5924.3977 | F26: =IF(25<=RecLag,0,INDEX(Port_Defaults,25-RecLag)*RecoveryRate) -> 4540.4188 | G26: =B26*(CPR/12) -> 3554.6386 | H26: =FeePct*(C26+D26+F26) -> 1374.9599 | I26: =C26+D26+F26-E26-G26-H26 -> 126641.99 | J26: =B26-(D26+E26+G26) -> 1293888.5
A27: 26 | B27: =J26 -> 1293888.5 | C27: =B27*0.122102/12 -> 13165.531 | D27: =MIN(B27,B27/11) -> 117626.22 | E27: =B27*(ADR_Base/12) -> 5391.2019 | F27: =IF(26<=RecLag,0,INDEX(Port_Defaults,26-RecLag)*RecoveryRate) -> 4207.4548 | G27: =B27*(CPR/12) -> 3234.7212 | H27: =FeePct*(C27+D27+F27) -> 1349.9921 | I27: =C27+D27+F27-E27-G27-H27 -> 125023.29 | J27: =B27-(D27+E27+G27) -> 1167636.3
A28: 27 | B28: =J27 -> 1167636.3 | C28: =B28*0.122102/12 -> 11880.894 | D28: =MIN(B28,B28/10) -> 116763.63 | E28: =B28*(ADR_Base/12) -> 4865.1513 | F28: =IF(27<=RecLag,0,INDEX(Port_Defaults,27-RecLag)*RecoveryRate) -> 3878.8726 | G28: =B28*(CPR/12) -> 2919.0908 | H28: =FeePct*(C28+D28+F28) -> 1325.234 | I28: =C28+D28+F28-E28-G28-H28 -> 123413.92 | J28: =B28-(D28+E28+G28) -> 1043088.4
A29: 28 | B29: =J28 -> 1043088.4 | C29: =B29*0.122102/12 -> 10613.599 | D29: =MIN(B29,B29/9) -> 115898.72 | E29: =B29*(ADR_Base/12) -> 4346.2018 | F29: =IF(28<=RecLag,0,INDEX(Port_Defaults,28-RecLag)*RecoveryRate) -> 3554.6386 | G29: =B29*(CPR/12) -> 2607.7211 | H29: =FeePct*(C29+D29+F29) -> 1300.6695 | I29: =C29+D29+F29-E29-G29-H29 -> 121812.36 | J29: =B29-(D29+E29+G29) -> 920235.8
A30: 29 | B30: =J29 -> 920235.8 | C30: =B30*0.122102/12 -> 9363.5527 | D30: =MIN(B30,B30/8) -> 115029.48 | E30: =B30*(ADR_Base/12) -> 3834.3158 | F30: =IF(29<=RecLag,0,INDEX(Port_Defaults,29-RecLag)*RecoveryRate) -> 3234.7212 | G30: =B30*(CPR/12) -> 2300.5895 | H30: =FeePct*(C30+D30+F30) -> 1276.2775 | I30: =C30+D30+F30-E30-G30-H30 -> 120216.57 | J30: =B30-(D30+E30+G30) -> 799071.42
A31: 30 | B31: =J30 -> 799071.42 | C31: =B31*0.122102/12 -> 8130.6849 | D31: =MIN(B31,B31/7) -> 114153.06 | E31: =B31*(ADR_Base/12) -> 3329.4643 | F31: =IF(30<=RecLag,0,INDEX(Port_Defaults,30-RecLag)*RecoveryRate) -> 2919.0908 | G31: =B31*(CPR/12) -> 1997.6786 | H31: =FeePct*(C31+D31+F31) -> 1252.0284 | I31: =C31+D31+F31-E31-G31-H31 -> 118623.66 | J31: =B31-(D31+E31+G31) -> 679591.22
A32: 31 | B32: =J31 -> 679591.22 | C32: =B32*0.122102/12 -> 6914.9539 | D32: =MIN(B32,B32/6) -> 113265.2 | E32: =B32*(ADR_Base/12) -> 2831.6301 | F32: =IF(31<=RecLag,0,INDEX(Port_Defaults,31-RecLag)*RecoveryRate) -> 2607.7211 | G32: =B32*(CPR/12) -> 1698.978 | H32: =FeePct*(C32+D32+F32) -> 1227.8788 | I32: =C32+D32+F32-E32-G32-H32 -> 117029.39 | J32: =B32-(D32+E32+G32) -> 561795.41
A33: 32 | B33: =J32 -> 561795.41 | C33: =B33*0.122102/12 -> 5716.3619 | D33: =MIN(B33,B33/5) -> 112359.08 | E33: =B33*(ADR_Base/12) -> 2340.8142 | F33: =IF(32<=RecLag,0,INDEX(Port_Defaults,32-RecLag)*RecoveryRate) -> 2300.5895 | G33: =B33*(CPR/12) -> 1404.4885 | H33: =FeePct*(C33+D33+F33) -> 1203.7603 | I33: =C33+D33+F33-E33-G33-H33 -> 115426.97 | J33: =B33-(D33+E33+G33) -> 445691.02
A34: 33 | B34: =J33 -> 445691.02 | C34: =B34*0.122102/12 -> 4534.9804 | D34: =MIN(B34,B34/4) -> 111422.76 | E34: =B34*(ADR_Base/12) -> 1857.0459 | F34: =IF(33<=RecLag,0,INDEX(Port_Defaults,33-RecLag)*RecoveryRate) -> 1997.6786 | G34: =B34*(CPR/12) -> 1114.2276 | H34: =FeePct*(C34+D34+F34) -> 1179.5541 | I34: =C34+D34+F34-E34-G34-H34 -> 113804.59 | J34: =B34-(D34+E34+G34) -> 331296.99
A35: 34 | B35: =J34 -> 331296.99 | C35: =B35*0.122102/12 -> 3371.0021 | D35: =MIN(B35,B35/3) -> 110432.33 | E35: =B35*(ADR_Base/12) -> 1380.4041 | F35: =IF(34<=RecLag,0,INDEX(Port_Defaults,34-RecLag)*RecoveryRate) -> 1698.978 | G35: =B35*(CPR/12) -> 828.24249 | H35: =FeePct*(C35+D35+F35) -> 1155.0231 | I35: =C35+D35+F35-E35-G35-H35 -> 112138.64 | J35: =B35-(D35+E35+G35) -> 218656.02
A36: 35 | B36: =J35 -> 218656.02 | C36: =B36*0.122102/12 -> 2224.8614 | D36: =MIN(B36,B36/2) -> 109328.01 | E36: =B36*(ADR_Base/12) -> 911.06673 | F36: =IF(35<=RecLag,0,INDEX(Port_Defaults,35-RecLag)*RecoveryRate) -> 1404.4885 | G36: =B36*(CPR/12) -> 546.64004 | H36: =FeePct*(C36+D36+F36) -> 1129.5736 | I36: =C36+D36+F36-E36-G36-H36 -> 110370.08 | J36: =B36-(D36+E36+G36) -> 107870.3
A37: 36 | B37: =J36 -> 107870.3 | C37: =B37*0.122102/12 -> 1097.5983 | D37: =MIN(B37,B37/1) -> 107870.3 | E37: =B37*(ADR_Base/12) -> 449.45959 | F37: =IF(36<=RecLag,0,INDEX(Port_Defaults,36-RecLag)*RecoveryRate) -> 1114.2276 | G37: =B37*(CPR/12) -> 269.67575 | H37: =FeePct*(C37+D37+F37) -> 1100.8213 | I37: =C37+D37+F37-E37-G37-H37 -> 108262.17 | J37: =B37-(D37+E37+G37) -> -719.13534

Sheet Waterfall
A1: Month | B1: Collections | C1: Sr_BegBal | D1: Mz_BegBal | E1: Eq_BegBal | F1: Sr_Int | G1: Mz_Int | H1: Sr_Principal | I1: Mz_Principal | J1: Fees_Addl | K1: Residual_to_Equity | L1: Sr_EndBal | M1: Mz_EndBal | N1: Eq_Cash
A2: 1 | B2: =Portfolio_CF!I2 -> 155967.81 | C2: =Sr_Notes -> 3355856 | D2: =Mz_Notes -> 958816 | E2: 0 | F2: =C2*(SeniorRate/12) -> 16779.28 | G2: =D2*(MezzRate/12) -> 7191.12 | H2: =MAX(0, MIN(C2, B2-F2-G2)) -> 131997.41 | I2: =MAX(0, MIN(D2, B2-F2-G2-H2)) -> 0 | J2: 0 | K2: =MAX(0, B2-F2-G2-H2-I2-J2) -> 0 | L2: =C2-H2 -> 3223858.6 | M2: =D2-I2 -> 958816 | N2: =K2 -> 0
A3: 2 | B3: =Portfolio_CF!I3 -> 154424.05 | C3: =L2 -> 3223858.6 | D3: =M2 -> 958816 | E3: 0 | F3: =C3*(SeniorRate/12) -> 16119.293 | G3: =D3*(MezzRate/12) -> 7191.12 | H3: =MAX(0, MIN(C3, B3-F3-G3)) -> 131113.63 | I3: =MAX(0, MIN(D3, B3-F3-G3-H3)) -> 0 | J3: 0 | K3: =MAX(0, B3-F3-G3-H3-I3-J3) -> 0 | L3: =C3-H3 -> 3092745 | M3: =D3-I3 -> 958816 | N3: =K3 -> 0
A4: 3 | B4: =Portfolio_CF!I4 -> 152893.25 | C4: =L3 -> 3092745 | D4: =M3 -> 958816 | E4: 0 | F4: =C4*(SeniorRate/12) -> 15463.725 | G4: =D4*(MezzRate/12) -> 7191.12 | H4: =MAX(0, MIN(C4, B4-F4-G4)) -> 130238.41 | I4: =MAX(0, MIN(D4, B4-F4-G4-H4)) -> 0 | J4: 0 | K4: =MAX(0, B4-F4-G4-H4-I4-J4) -> 0 | L4: =C4-H4 -> 2962506.5 | M4: =D4-I4 -> 958816 | N4: =K4 -> 0
A5: 4 | B5: =Portfolio_CF!I5 -> 163865.13 | C5: =L4 -> 2962506.5 | D5: =M4 -> 958816 | E5: 0 | F5: =C5*(SeniorRate/12) -> 14812.533 | G5: =D5*(MezzRate/12) -> 7191.12 | H5: =MAX(0, MIN(C5, B5-F5-G5)) -> 141861.48 | I5: =MAX(0, MIN(D5, B5-F5-G5-H5)) -> 0 | J5: 0 | K5: =MAX(0, B5-F5-G5-H5-I5-J5) -> 0 | L5: =C5-H5 -> 2820645.1 | M5: =D5-I5 -> 958816 | N5: =K5 -> 0
A6: 5 | B6: =Portfolio_CF!I6 -> 161929.65 | C6: =L5 -> 2820645.1 | D6: =M5 -> 958816 | E6: 0 | F6: =C6*(SeniorRate/12) -> 14103.225 | G6: =D6*(MezzRate/12) -> 7191.12 | H6: =MAX(0, MIN(C6, B6-F6-G6)) -> 140635.3 | I6: =MAX(0, MIN(D6, B6-F6-G6-H6)) -> 0 | J6: 0 | K6: =MAX(0, B6-F6-G6-H6-I6-J6) -> 0 | L6: =C6-H6 -> 2680009.8 | M6: =D6-I6 -> 958816 | N6: =K6 -> 0
A7: 6 | B7: =Portfolio_CF!I7 -> 160011.96 | C7: =L6 -> 2680009.8 | D7: =M6 -> 958816 | E7: 0 | F7: =C7*(SeniorRate/12) -> 13400.049 | G7: =D7*(MezzRate/12) -> 7191.12 | H7: =MAX(0, MIN(C7, B7-F7-G7)) -> 139420.79 | I7: =MAX(0, MIN(D7, B7-F7-G7-H7)) -> 0 | J7: 0 | K7: =MAX(0, B7-F7-G7-H7-I7-J7) -> 0 | L7: =C7-H7 -> 2540589 | M7: =D7-I7 -> 958816 | N7: =K7 -> 0
A8: 7 | B8: =Portfolio_CF!I8 -> 158111.85 | C8: =L7 -> 2540589 | D8: =M7 -> 958816 | E8: 0 | F8: =C8*(SeniorRate/12) -> 12702.945 | G8: =D8*(MezzRate/12) -> 7191.12 | H8: =MAX(0, MIN(C8, B8-F8-G8)) -> 138217.78 | I8: =MAX(0, MIN(D8, B8-F8-G8-H8)) -> 0 | J8: 0 | K8: =MAX(0, B8-F8-G8-H8-I8-J8) -> 0 | L8: =C8-H8 -> 2402371.2 | M8: =D8-I8 -> 958816 | N8: =K8 -> 0
A9: 8 | B9: =Portfolio_CF!I9 -> 156229.12 | C9: =L8 -> 2402371.2 | D9: =M8 -> 958816 | E9: 0 | F9: =C9*(SeniorRate/12) -> 12011.856 | G9: =D9*(MezzRate/12) -> 7191.12 | H9: =MAX(0, MIN(C9, B9-F9-G9)) -> 137026.14 | I9: =MAX(0, MIN(D9, B9-F9-G9-H9)) -> 0 | J9: 0 | K9: =MAX(0, B9-F9-G9-H9-I9-J9) -> 0 | L9: =C9-H9 -> 2265345.1 | M9: =D9-I9 -> 958816 | N9: =K9 -> 0
A10: 9 | B10: =Portfolio_CF!I10 -> 154363.56 | C10: =L9 -> 2265345.1 | D10: =M9 -> 958816 | E10: 0 | F10: =C10*(SeniorRate/12) -> 11326.725 | G10: =D10*(MezzRate/12) -> 7191.12 | H10: =MAX(0, MIN(C10, B10-F10-G10)) -> 135845.72 | I10: =MAX(0, MIN(D10, B10-F10-G10-H10)) -> 0 | J10: 0 | K10: =MAX(0, B10-F10-G10-H10-I10-J10) -> 0 | L10: =C10-H10 -> 2129499.3 | M10: =D10-I10 -> 958816 | N10: =K10 -> 0
A11: 10 | B11: =Portfolio_CF!I11 -> 152514.97 | C11: =L10 -> 2129499.3 | D11: =M10 -> 958816 | E11: 0 | F11: =C11*(SeniorRate/12) -> 10647.497 | G11: =D11*(MezzRate/12) -> 7191.12 | H11: =MAX(0, MIN(C11, B11-F11-G11)) -> 134676.35 | I11: =MAX(0, MIN(D11, B11-F11-G11-H11)) -> 0 | J11: 0 | K11: =MAX(0, B11-F11-G11-H11-I11-J11) -> 0 | L11: =C11-H11 -> 1994823 | M11: =D11-I11 -> 958816 | N11: =K11 -> 0
A12: 11 | B12: =Portfolio_CF!I12 -> 150683.12 | C12: =L11 -> 1994823 | D12: =M11 -> 958816 | E12: 0 | F12: =C12*(SeniorRate/12) -> 9974.1149 | G12: =D12*(MezzRate/12) -> 7191.12 | H12: =MAX(0, MIN(C12, B12-F12-G12)) -> 133517.88 | I12: =MAX(0, MIN(D12, B12-F12-G12-H12)) -> 0 | J12: 0 | K12: =MAX(0, B12-F12-G12-H12-I12-J12) -> 0 | L12: =C12-H12 -> 1861305.1 | M12: =D12-I12 -> 958816 | N12: =K12 -> 0
A13: 12 | B13: =Portfolio_CF!I13 -> 148867.78 | C13: =L12 -> 1861305.1 | D13: =M12 -> 958816 | E13: 0 | F13: =C13*(SeniorRate/12) -> 9306.5255 | G13: =D13*(MezzRate/12) -> 7191.12 | H13: =MAX(0, MIN(C13, B13-F13-G13)) -> 132370.14 | I13: =MAX(0, MIN(D13, B13-F13-G13-H13)) -> 0 | J13: 0 | K13: =MAX(0, B13-F13-G13-H13-I13-J13) -> 0 | L13: =C13-H13 -> 1728935 | M13: =D13-I13 -> 958816 | N13: =K13 -> 0
A14: 13 | B14: =Portfolio_CF!I14 -> 147068.73 | C14: =L13 -> 1728935 | D14: =M13 -> 958816 | E14: 0 | F14: =C14*(SeniorRate/12) -> 8644.6749 | G14: =D14*(MezzRate/12) -> 7191.12 | H14: =MAX(0, MIN(C14, B14-F14-G14)) -> 131232.94 | I14: =MAX(0, MIN(D14, B14-F14-G14-H14)) -> 0 | J14: 0 | K14: =MAX(0, B14-F14-G14-H14-I14-J14) -> 0 | L14: =C14-H14 -> 1597702 | M14: =D14-I14 -> 958816 | N14: =K14 -> 0
... A37: 36 | B37: =Portfolio_CF!I37 -> 108262.17 | C37: =L36 -> 0 | D37: =M36 -> 0 | E37: 0 | F37: =C37*(SeniorRate/12) -> 0 | G37: =D37*(MezzRate/12) -> 0 | H37: =MAX(0, MIN(C37, B37-F37-G37)) -> 0 | I37: =MAX(0, MIN(D37, B37-F37-G37-H37)) -> 0 | J37: 0 | K37: =MAX(0, B37-F37-G37-H37-I37-J37) -> 108262.17 | L37: =C37-H37 -> 0 | M37: =D37-I37 -> 0 | N37: =K37 -> 108262.17

Sheet Tranche_Summary
A1: Metric | B1: Senior | C1: Mezz | D1: Equity
A3: Initial Investment | B3: =-Sr_Notes -> -3355856 | C3: =-Mz_Notes -> -958816 | D3: 0
A4: Sum of Cash Inflows (periodic) | B4: =SUM(Waterfall!F2:F37)+SUM(Waterfall!H2:H37) -> 3575820.8 | C4: =SUM(Waterfall!G2:G37)+SUM(Waterfall!I2:I37) -> 1178948.3 | D4: =SUM(Waterfall!N2:N37) -> 178324.38
A6: IRR (Monthly) | B6: =IFERROR(IRR(B12:B48),NA()) -> 0.005 | C6: =IFERROR(IRR(C12:C48),NA()) -> 0.0075 | D6: =IFERROR(IRR(D12:D48),NA()) -> #N/A
A7: IRR (Annualized approx) | B7: =(1+B6)^12-1 -> 0.061677812 | C7: =(1+C6)^12-1 -> 0.093806898 | D7: =(1+D6)^12-1 -> #N/A
A9: WAL (months) | B9: =SUMPRODUCT(Waterfall!$A$2:$A$37,Waterfall!$H$2:$H$37)/SUM(Waterfall!$H$2:$H$37) -> 13.109312 | C9: =SUMPRODUCT(Waterfall!$A$2:$A$37,Waterfall!$I$2:$I$37)/SUM(Waterfall!$I$2:$I$37) -> 30.611685 | D9: -
A11: CF Series (for IRR)
B12: =-Sr_Notes -> -3355856 | C12: =-Mz_Notes -> -958816 | D12: 0
B13: =Waterfall!F2+Waterfall!H2 -> 148776.69 | C13: =Waterfall!G2+Waterfall!I2 -> 7191.12 | D13: =Waterfall!N2 -> 0
B14: =Waterfall!F3+Waterfall!H3 -> 147232.93 | C14: =Waterfall!G3+Waterfall!I3 -> 7191.12 | D14: =Waterfall!N3 -> 0
B15: =Waterfall!F4+Waterfall!H4 -> 145702.13 | C15: =Waterfall!G4+Waterfall!I4 -> 7191.12 | D15: =Waterfall!N4 -> 0
B16: =Waterfall!F5+Waterfall!H5 -> 156674.01 | C16: =Waterfall!G5+Waterfall!I5 -> 7191.12 | D16: =Waterfall!N5 -> 0
B17: =Waterfall!F6+Waterfall!H6 -> 154738.53 | C17: =Waterfall!G6+Waterfall!I6 -> 7191.12 | D17: =Waterfall!N6 -> 0
B18: =Waterfall!F7+Waterfall!H7 -> 152820.84 | C18: =Waterfall!G7+Waterfall!I7 -> 7191.12 | D18: =Waterfall!N7 -> 0
B19: =Waterfall!F8+Waterfall!H8 -> 150920.73 | C19: =Waterfall!G8+Waterfall!I8 -> 7191.12 | D19: =Waterfall!N8 -> 0
B20: =Waterfall!F9+Waterfall!H9 -> 149038 | C20: =Waterfall!G9+Waterfall!I9 -> 7191.12 | D20: =Waterfall!N9 -> 0
B21: =Waterfall!F10+Waterfall!H10 -> 147172.44 | C21: =Waterfall!G10+Waterfall!I10 -> 7191.12 | D21: =Waterfall!N10 -> 0
B22: =Waterfall!F11+Waterfall!H11 -> 145323.85 | C22: =Waterfall!G11+Waterfall!I11 -> 7191.12 | D22: =Waterfall!N11 -> 0
B23: =Waterfall!F12+Waterfall!H12 -> 143492 | C23: =Waterfall!G12+Waterfall!I12 -> 7191.12 | D23: =Waterfall!N12 -> 0
B24: =Waterfall!F13+Waterfall!H13 -> 141676.66 | C24: =Waterfall!G13+Waterfall!I13 -> 7191.12 | D24: =Waterfall!N13 -> 0
... B48: =Waterfall!F37+Waterfall!H37 -> 0 | C48: =Waterfall!G37+Waterfall!I37 -> 0 | D48: =Waterfall!N37 -> 108262.17

Sheet DASHBOARD
A1: ABS Waterfall – One‑Pager (Export)
A3: Initial Pool | B3: =Assumptions!B2 -> 5046400 | D3: Senior IRR (ann.) | E3: =(1+Tranche_Summary!B6)^1-1 -> 0.005
A4: Default Rate | B4: =Assumptions!B3 -> 0.05 | D4: Mezz IRR (ann.) | E4: =(1+Tranche_Summary!C6)^1-1 -> 0.0075
A5: Recovery Rate | B5: =Assumptions!B5 -> 0.6 | D5: Equity IRR (ann.) | E5: =(1+Tranche_Summary!D6)^1-1 -> #N/A
A6: CPR | B6: =Assumptions!B6 -> 0.03
A7: Total Collections | B7: =SUM(Waterfall!B2:B37) -> 4933093.5 | D7: WAL Senior (mo) | E7: =Tranche_Summary!B9 -> 13.109312
A8: Equity Residual (Total) | B8: =SUM(Waterfall!N2:N37) -> 178324.38 | D8: WAL Mezz (mo) | E8: =Tranche_Summary!C9 -> 30.611685
